[
    { "id": 1,
      "nombre": "Música Funcional de Hospital", 
      "descripcion": "¿La espera lo dejó moviendo la cabeza? ¿Sigue pensando en ese solo de guitarra? ¡Ahora puede volver a cada disfrutando el sonido que lo curó!", 
      "precio": 10,
      "unidadesDisponibles": 1000,
      "agregado": 0,
      "unidadesPedidas": 0,
      "fotoproducto":"../assets/shop/cd.png"
    },
    { "id": 2,
      "nombre": "Vacunas", 
      "descripcion": "¿Tiene su calendario de vacunación al día? ¿Y sus hijos? ¿Y sus perros? Vengan que hay vacunas para todos. Alguien será vacunado", 
      "precio": 100,
      "unidadesDisponibles": 38212,
      "agregado": 0,
      "unidadesPedidas": 0,
      "fotoproducto":"../assets/shop/vacunas.png"
    },
    { "id": 3, 
      "nombre": "Pool y esparcimiento", 
    "descripcion": "Sí, tenemos un pool y esta a la venta. La tele va de regalo (Ya nos compramos un 4k)", 
    "precio": 10000,
    "unidadesDisponibles": 1,
    "agregado": 0,
    "unidadesPedidas": 0,
    "fotoproducto":"../assets/shop/pool.png"
    },
    { "id": 4,
      "nombre": "KitKat", 
    "descripcion": "Y sí, es totalmente logico que un hospital venda chips no recomendado para diabeticos, niños y enfermos en general.", 
    "precio": 1.5,
    "unidadesDisponibles": 1000000,
    "agregado": 0,
    "unidadesPedidas": 0,
    "fotoproducto":"../assets/shop/kitkat.png"
    },
    { "id": 5,
      "nombre": "Fax", 
    "descripcion": "Moderna Maquina de comunicación. Imagine que tiene que mandar una imagen. ¿Cómo lo resuelve? ¡Correcto! Por fax", 
    "precio": 10,
    "unidadesDisponibles": 8,
    "agregado": 0,
    "unidadesPedidas": 0,
    "fotoproducto":"../assets/shop/fax.png"
    },
    { "id": 6,
      "nombre": "Cronometro", 
    "descripcion": "Con nuestro cronometro oficial usted prodrá demostrarnos todo el tiempo que lo tuvimos en sala de espera", 
    "precio": 5,
    "unidadesDisponibles": 351156,
    "agregado": 0,
    "unidadesPedidas": 0,
    "fotoproducto":"../assets/shop/cronometro.png" 
    },
    { "id": 7,
      "nombre": "Helicóptero", 
      "descripcion": "Nos quedamos sin chofer y no conseguimos otro. Esta a la venta. No será un Halcón negro pero puede llevarte rapido a cualquier lado", 
      "precio": 50000,
      "unidadesDisponibles": 1,
      "agregado": 0,
      "unidadesPedidas": 0,
      "fotoproducto":"../assets/shop/helicopter.png"
    },
    { "id": 8,
      "nombre": "Cinta para correr", 
      "descripcion": "¿No sabes qué hacer con la ropa que traes de la calle? Esta es una idea para usar como perchero... y, de última, para correr.", 
      "precio": 3000,
      "unidadesDisponibles": 7,
      "agregado": 0,
      "unidadesPedidas": 0,
      "fotoproducto":"../assets/shop/Cardiogram.png"
    },
    { "id": 9,
      "nombre": "Maquina de Coso", 
      "descripcion": "Nos dijeron que era para cosas médicas, pero nunca supimos cuáles. Tampoco entendimos el manual. En fin, ¡a la venta!", 
      "precio": 15232,
      "unidadesDisponibles": 1,
      "agregado": 0,
      "unidadesPedidas": 0,
      "fotoproducto":"../assets/shop/maquina.png"
    },
    { "id": 10,
      "nombre": "Maquina en desuso", 
      "descripcion": "La dejamos de usar porque se prendió fuego y se calcinó. Ya no la necesitamos, así que ¡la vendemos!", 
      "precio": 1,
      "unidadesDisponibles": 1,
      "agregado": 0,
      "unidadesPedidas": 0,
      "fotoproducto":"../assets/shop/disaster.png"
    },
    { "id": 11,
      "nombre": "Proyector", 
      "descripcion": "Podés ver cualquier película que haya salido de 1968 para atrás en el living de tu casa.", 
      "precio": 60,
      "unidadesDisponibles": 3,
      "agregado": 0,
      "unidadesPedidas": 0,
      "fotoproducto":"../assets/shop/proyector.png"
    },
    { "id": 12,
      "nombre": "Matafuego", 
      "descripcion": "Le rayas la fecha de vencimiento y listo, te queda un matafuego listo para usar en tu casa.", 
      "precio": 5,
      "unidadesDisponibles": 106,
      "agregado": 0,
      "unidadesPedidas": 0,
      "fotoproducto":"../assets/shop/matafuego.png"
    },
    { "id": 13,
      "nombre": "Tachos", 
      "descripcion": "Algunos dirán que fueron tachos de basura. Serán envidisos de semejante invento ingenieril.", 
      "precio": 3,
      "unidadesDisponibles": 208,
      "agregado": 0,
      "unidadesPedidas": 0,
      "fotoproducto":"../assets/shop/tacho.png"
    },
    { "id": 14,
      "nombre": "Radiadores", 
      "descripcion": "Son radiadores para calentar el lugar. No los del auto. No sabemos a qué hay que conectarlos.", 
      "precio": 30,
      "unidadesDisponibles": 35,
      "agregado": 0,
      "unidadesPedidas": 0,
      "fotoproducto":"../assets/shop/estufas.png"
    },
    { "id": 15,
      "nombre": "Plantas", 
      "descripcion": "Re deprimente tener plantas en un hospital. Además un bajón regarlas. PReferimos poner otras falsas en su lugar.", 
      "precio": 2,
      "unidadesDisponibles": 1650,
      "agregado": 0,
      "unidadesPedidas": 0,
      "fotoproducto":"../assets/shop/plantas.png"
    },
    { "id": 16,
      "nombre": "Mueble", 
      "descripcion": "Entre nos, si lo pones en el living de tu casa nadie se va a dar cuenta que era de un hospital. Le tenés que sacar los libros vos antes de llevarlo.", 
      "precio": 80,
      "unidadesDisponibles": 12,
      "agregado": 0,
      "unidadesPedidas": 0,
      "fotoproducto":"../assets/shop/mueble.png"
    },
    { "id": 17,
      "nombre": "Felipe", 
      "descripcion": "Felipe era nuestro esqueleto. El nombre se lo puso mi abuelo. Lo vamos a sacar de la sala de investigaciones para poner una Nespresso.", 
      "precio": 1000,
      "unidadesDisponibles": 1,
      "agregado": 0,
      "unidadesPedidas": 0,
      "fotoproducto":"../assets/shop/esqueleto.png"
    },
    { "id": 18,
      "nombre": "Escritorio", 
      "descripcion": "Son un par de estos que teníamos en la recepción. Vamos a reemplazarlos con otros estilo nórdico.", 
      "precio": 16,
      "unidadesDisponibles": 5,
      "agregado": 0,
      "unidadesPedidas": 0,
      "fotoproducto":"../assets/shop/Escritorio.png"
    }
]